summarizer/__init__.py
summarizer/cohesion_sumamrizer.py
summarizer/key_words.py
summarizer/preprocessing.py
summarizer/summarizer.py
summarizer/summarizer_algorithm.py
summarizer/test.py
summarizer/libs/__init__.py
summarizer/libs/common.py
coh_summarizer-0.2.dist-info/LICENSE.txt
coh_summarizer-0.2.dist-info/METADATA
coh_summarizer-0.2.dist-info/WHEEL
coh_summarizer-0.2.dist-info/top_level.txt
coh_summarizer-0.2.dist-info/RECORD
