Metadata-Version: 2.1
Name: coh-summarizer
Version: 0.2
Summary: Summarizer tool
Home-page: https://github.com/ZILiAT-NASK/Summarizer
Author: ZILiAT-NASK, Adam Nowakowski
Author-email: adam.nowakowski@nask.pl
Classifier: Programming Language :: Python :: 3
Classifier: License :: OSI Approved :: GNU General Public License v3 (GPLv3)
Classifier: Operating System :: OS Independent
Requires-Python: >=3.6
License-File: LICENSE.txt
Requires-Dist: setuptools (>=49.2.0)
Requires-Dist: numpy (>=1.17.0)
Requires-Dist: pandas (>=1.0.5)
Requires-Dist: scikit-learn
Requires-Dist: spacy
Requires-Dist: spacy-syllables (==3.0.1)
Requires-Dist: spacy-transformers
Requires-Dist: morfeusz2
Requires-Dist: pexpect
